konsave/__init__.py
konsave/__main__.py
konsave/conf_kde.yaml
konsave/conf_other.yaml
konsave/consts.py
konsave/funcs.py
konsave/parse.py
konsave-2.3.0.dist-info/licenses/LICENSE
konsave-2.3.0.dist-info/METADATA
konsave-2.3.0.dist-info/WHEEL
konsave-2.3.0.dist-info/entry_points.txt
konsave-2.3.0.dist-info/top_level.txt
konsave-2.3.0.dist-info/RECORD
