Metadata-Version: 2.4
Name: Konsave
Version: 2.3.0
Summary: A program that lets you save your Plasma configuration in an instant!
Home-page: https://www.github.com/prayag2/konsave/
Author: Prayag Jain
Author-email: prayagjain2@gmail.com
Classifier: License :: OSI Approved :: GNU General Public License v3 or later (GPLv3+)
Classifier: Operating System :: POSIX
Classifier: Environment :: Console
Classifier: Intended Audience :: End Users/Desktop
Classifier: Programming Language :: Python
Requires-Python: >=3.6
License-File: LICENSE
Requires-Dist: PyYaml>=5.4.1
Requires-Dist: setuptools>=75.1.0
Provides-Extra: dev
Requires-Dist: aiohttp>=3.7.4; extra == "dev"
Requires-Dist: aiohttp_cors>=0.7.0; extra == "dev"
Requires-Dist: black>=20.8b1; extra == "dev"
Requires-Dist: pylint>=2.7.2; extra == "dev"
Dynamic: author
Dynamic: author-email
Dynamic: classifier
Dynamic: description
Dynamic: description-content-type
Dynamic: home-page
Dynamic: license-file
Dynamic: provides-extra
Dynamic: requires-dist
Dynamic: requires-python
Dynamic: summary
